lief/ART/__init__.pyi
lief/Android/__init__.pyi
lief/COFF/__init__.pyi
lief/DEX/__init__.pyi
lief/ELF/__init__.pyi
lief/MachO/__init__.pyi
lief/OAT/__init__.pyi
lief/PE/__init__.pyi
lief/PE/unwind_aarch64/__init__.pyi
lief/PE/unwind_x64/__init__.pyi
lief/VDEX/__init__.pyi
lief/__init__.py
lief/__init__.pyi
lief/_lief.pyd
lief/assembly/__init__.pyi
lief/assembly/aarch64/__init__.pyi
lief/assembly/aarch64/operands/__init__.pyi
lief/assembly/arm/__init__.pyi
lief/assembly/ebpf/__init__.pyi
lief/assembly/mips/__init__.pyi
lief/assembly/powerpc/__init__.pyi
lief/assembly/riscv/__init__.pyi
lief/assembly/x86/__init__.pyi
lief/assembly/x86/operands/__init__.pyi
lief/dsc/__init__.pyi
lief/dwarf/__init__.pyi
lief/dwarf/editor/__init__.pyi
lief/dwarf/parameters/__init__.pyi
lief/dwarf/types/__init__.pyi
lief/logging/__init__.pyi
lief/objc/__init__.pyi
lief/pdb/__init__.pyi
lief/pdb/types/__init__.pyi
lief/py.typed
lief-0.17.3.dist-info/METADATA
lief-0.17.3.dist-info/WHEEL
lief-0.17.3.dist-info/RECORD
