Metadata-Version: 2.2
Name: lief
Version: 0.17.3
Summary: Library to instrument executable formats
Keywords: parser,elf,pe,macho,reverse-engineering
Author-Email: Romain Thomas <contact@lief.re>
License: Apache License 2.0
Classifier: Development Status :: 4 - Beta
Classifier: Programming Language :: Python :: 3
Classifier: Programming Language :: C++
Classifier: Topic :: Software Development :: Libraries
Project-URL: homepage, https://lief-project.github.io/
Project-URL: documentation, https://lief-project.github.io/doc/latest/
Project-URL: repository, https://github.com/lief-project/LIEF
Project-URL: changelog, https://lief-project.github.io/doc/latest/changelog.html
Project-URL: Funding, https://github.com/sponsors/lief-project
Project-URL: Tracker, https://github.com/lief-project/LIEF/issues
Requires-Python: >=3.8
